{
    "gui": {
        "editor_gaphas": {
            "name": {
                "rel_pos": {
                    "__jsonqualname__": "__builtin__.tuple", 
                    "items": [
                        0.8700646130473615, 
                        0.8700646130473757
                    ]
                }, 
                "size": {
                    "__jsonqualname__": "__builtin__.tuple", 
                    "items": [
                        20.011486100089577, 
                        8.70064613047373
                    ]
                }
            }, 
            "rel_pos": {
                "__jsonqualname__": "__builtin__.tuple", 
                "items": [
                    170.5973483261706, 
                    54.37903831546081
                ]
            }, 
            "size": {
                "__jsonqualname__": "__builtin__.tuple", 
                "items": [
                    21.751615326184325, 
                    21.751615326184325
                ]
            }
        }, 
        "show_content": {}
    }, 
    "income": {
        "gui": {
            "editor_gaphas": {
                "rel_pos": {
                    "__jsonqualname__": "__builtin__.tuple", 
                    "items": [
                        0.0, 
                        2.1751615326184326
                    ]
                }
            }
        }
    }, 
    "input_data_port0": {
        "gui": {
            "editor_gaphas": {
                "rel_pos": {
                    "__jsonqualname__": "__builtin__.tuple", 
                    "items": [
                        0.0, 
                        19.576453793565893
                    ]
                }
            }
        }
    }, 
    "outcome-1": {
        "gui": {
            "editor_gaphas": {
                "rel_pos": {
                    "__jsonqualname__": "__builtin__.tuple", 
                    "items": [
                        19.576453793565893, 
                        0.0
                    ]
                }
            }
        }
    }, 
    "outcome-2": {
        "gui": {
            "editor_gaphas": {
                "rel_pos": {
                    "__jsonqualname__": "__builtin__.tuple", 
                    "items": [
                        17.83632456747115, 
                        0.0
                    ]
                }
            }
        }
    }, 
    "outcome0": {
        "gui": {
            "editor_gaphas": {
                "rel_pos": {
                    "__jsonqualname__": "__builtin__.tuple", 
                    "items": [
                        21.751615326184325, 
                        2.1751615326184326
                    ]
                }
            }
        }
    }
}